nonebot_plugin_ehentai-0.1.2.dist-info/METADATA
nonebot_plugin_ehentai-0.1.2.dist-info/WHEEL
nonebot_plugin_ehentai-0.1.2.dist-info/entry_points.txt
nonebot_plugin_ehentai-0.1.2.dist-info/licenses/LICENSE
nonebot_plugin_ehentai/__init__.py
nonebot_plugin_ehentai/config.py
nonebot_plugin_ehentai/ehapi.py
nonebot_plugin_ehentai/utils.py
nonebot_plugin_ehentai-0.1.2.dist-info/RECORD
