Metadata-Version: 2.1
Name: nonebot-plugin-ehentai
Version: 0.1.2
Summary: 下载eh本子并发送
License: MIT
Project-URL: homepage, https://github.com/MaxCrazy1101/nonebot-plugin-ehentai
Project-URL: repository, https://github.com/MaxCrazy1101/nonebot-plugin-ehentai
Requires-Python: >=3.10
Requires-Dist: aiofiles>=24.1.0
Requires-Dist: aiohttp>=3.11.18
Requires-Dist: img2pdf<1.0.0,>=0.6.1
Requires-Dist: nonebot-plugin-alconna<1.0.0,>=0.54.2
Requires-Dist: nonebot-plugin-apscheduler<1.0.0,>=0.5.0
Requires-Dist: nonebot-plugin-localstore<1.0.0,>=0.7.4
Requires-Dist: nonebot2<3.0.0,>=2.4.1
Requires-Dist: pypdf>=5.4.0
